LICENSE
MANIFEST.in
README.rst
VERSION
setup.py
bin/squire
squire/__init__.py
squire/squire.py
squire.egg-info/PKG-INFO
squire.egg-info/SOURCES.txt
squire.egg-info/dependency_links.txt
squire.egg-info/top_level.txt