Metadata-Version: 1.0
Name: squire
Version: 0.0.1
Summary: Watch a directory and run a command on changes
Home-page: https://github.com/charlesthomas/squire
Author: Charles Thomas
Author-email: ch@rlesthom.as
License: The MIT License (MIT)
